bubka/__init__.py
bubka/status.py
bubka-1.0.1.dist-info/METADATA
bubka-1.0.1.dist-info/WHEEL
bubka-1.0.1.dist-info/entry_points.txt
bubka-1.0.1.dist-info/top_level.txt
bubka-1.0.1.dist-info/RECORD
